snowflake/__init__.py
snowflake/__main__.py
tweetrelay/__init__.py
tweetrelay/_utils.py
tweetrelay/event.py
tweetrelay/processor.py
tweetrelay/server.py
tweetrelay/settings.py
tweetrelay/stream.py
tweetrelay-0.3.3.dist-info/LICENSE
tweetrelay-0.3.3.dist-info/METADATA
tweetrelay-0.3.3.dist-info/WHEEL
tweetrelay-0.3.3.dist-info/top_level.txt
tweetrelay-0.3.3.dist-info/RECORD
